.git_archival.txt
.gitattributes
.gitignore
.pre-commit-config.yaml
LICENSE.txt
README.md
environment.yml
mkdocs.yml
pyproject.toml
.github/FUNDING.yml
.github/actions/conda-setup/action.yml
.github/workflows/gh-pages.yml
.github/workflows/lint.yml
.github/workflows/pypi-upload.yml
.github/workflows/tests.yaml
bpy_lattice/__init__.py
bpy_lattice/_version.py
bpy_lattice/camera.py
bpy_lattice/constants.py
bpy_lattice/elements.py
bpy_lattice/lattice.py
bpy_lattice/materials.py
bpy_lattice/orbit.py
bpy_lattice/slicer.py
bpy_lattice.egg-info/PKG-INFO
bpy_lattice.egg-info/SOURCES.txt
bpy_lattice.egg-info/dependency_links.txt
bpy_lattice.egg-info/entry_points.txt
bpy_lattice.egg-info/requires.txt
bpy_lattice.egg-info/top_level.txt
bpy_lattice/interfaces/bmad.py
bpy_lattice/tests/test_import.py
bpy_lattice/tests/test_lattice.py
docs/index.md
docs/examples/bmad_interface_example.ipynb
docs/examples/test.ipynb
docs/overrides/main.html
examples/bmad/README.md
examples/bmad/bmad_to_blender.in
examples/bmad/lat.bmad
examples/bmad/lat.layout_table
scripts/execute_notebooks.bash
scripts/install_blender_package.sh
scripts/make_lattice.py