Metadata-Version: 2.2
Name: bpy-lattice
Version: 0.3.1
Summary: Tools for creating particle accelerator models in Blender
Author: Christopher Mayes
License:                                  Apache License
Project-URL: Homepage, https://github.com/ChristopherMayes/bpy-lattice
Classifier: Development Status :: 4 - Beta
Classifier: Natural Language :: English
Classifier: Programming Language :: Python :: 3
Classifier: Topic :: Scientific/Engineering
Requires-Python: >=3.9
License-File: LICENSE.txt
Requires-Dist: numpy<2
Requires-Dist: bpy
